textual_key_recorder/__init__.py
textual_key_recorder/__main__.py
textual_key_recorder/app.py
textual_key_recorder/dialogs/__init__.py
textual_key_recorder/dialogs/annotation.py
textual_key_recorder/dialogs/yes_no.py
textual_key_recorder/screens/__init__.py
textual_key_recorder/screens/main.py
textual_key_recorder/widgets/__init__.py
textual_key_recorder/widgets/environment.py
textual_key_recorder/widgets/expected_keys.py
textual_key_recorder/widgets/key_input.py
textual_key_recorder/widgets/keys_display.py
textual_key_recorder/widgets/notepad.py
textual_key_recorder/widgets/triggered_keys.py
textual_key_recorder/widgets/unexpected_keys.py
textual_key_recorder/widgets/unknown_keys.py
textual_key_recorder-0.1.4.dist-info/METADATA
textual_key_recorder-0.1.4.dist-info/WHEEL
textual_key_recorder-0.1.4.dist-info/entry_points.txt
textual_key_recorder-0.1.4.dist-info/RECORD
