Metadata-Version: 2.1
Name: textual-key-recorder
Version: 0.1.4
Summary: A tool to help record what key names are known to Textual
License: MIT
Author: Dave Pearson
Author-email: dave@textualize.io
Requires-Python: >=3.8,<4.0
Classifier: Development Status :: 4 - Beta
Classifier: Environment :: Console
Classifier: Intended Audience :: Developers
Classifier: License :: OSI Approved :: MIT License
Classifier: Operating System :: MacOS
Classifier: Operating System :: Microsoft :: Windows :: Windows 10
Classifier: Operating System :: Microsoft :: Windows :: Windows 11
Classifier: Operating System :: POSIX :: Linux
Classifier: Programming Language :: Python :: 3
Classifier: Programming Language :: Python :: 3.8
Classifier: Programming Language :: Python :: 3.9
Classifier: Programming Language :: Python :: 3.10
Classifier: Programming Language :: Python :: 3.11
Classifier: Programming Language :: Python :: 3.12
Classifier: Programming Language :: Python :: 3.7
Classifier: Typing :: Typed
Requires-Dist: textual (>=0.41.0)
Requires-Dist: textual-fspicker (>=0.0.10,<0.0.11)
